__init__.py
main.py
gulistandb-0.0.1.dist-info/License
gulistandb-0.0.1.dist-info/METADATA
gulistandb-0.0.1.dist-info/WHEEL
gulistandb-0.0.1.dist-info/top_level.txt
gulistandb-0.0.1.dist-info/RECORD
